napalm_mos/__init__.py
napalm_mos/constants.py
napalm_mos/mos.py
napalm_mos/utils/__init__.py
opti_napalm_mos-4.0.4.dist-info/AUTHORS
opti_napalm_mos-4.0.4.dist-info/LICENSE
opti_napalm_mos-4.0.4.dist-info/METADATA
opti_napalm_mos-4.0.4.dist-info/WHEEL
opti_napalm_mos-4.0.4.dist-info/top_level.txt
opti_napalm_mos-4.0.4.dist-info/RECORD
