Metadata-Version: 2.1
Name: opti-napalm-mos
Version: 4.0.4
Summary: Optiver's fork of NAPALM-MOS
Home-page: https://github.com/napalm-automation-community/napalm-mos
Author: Benny Holmgren, Brandon Ewing, 
Author-email: benny@holmgren.id.au, brandon.ewing@warningg.com, ams_pypi@optiver.com
License: UNKNOWN
Platform: UNKNOWN
Classifier: Topic :: Utilities
Classifier: Programming Language :: Python
Classifier: Operating System :: POSIX :: Linux
Classifier: Operating System :: MacOS
Requires-Python: >=3.7
License-File: LICENSE
License-File: AUTHORS
Requires-Dist: opti-napalm (>=4.0.0)
Requires-Dist: pyeapi (>=0.8.1)
